{"SessionScene":"Module_02_02","Id":"4","StartTime":"2022-07-13T14:19:19.24372Z","EndTime":null,"Student":{"Id":"0","FirstName":"NO NAME ENTERED","LastName":"","Sessions":{}},"Movements":{"0":{"Id":"0","Root":{"X":-1.4562397,"Y":10.0533276,"Z":-13.2474794},"Timestamp":"2022-07-13T10:19:23.407748-04:00"},"1":{"Id":"1","Root":{"X":-1.4562397,"Y":10.0533276,"Z":-13.2474794},"Timestamp":"2022-07-13T10:19:31.203786-04:00"},"2":{"Id":"2","Root":{"X":-1.4562397,"Y":10.0533276,"Z":-13.2474794},"Timestamp":"2022-07-13T10:19:31.913884-04:00"},"3":{"Id":"3","Root":{"X":-1.4562397,"Y":10.0533276,"Z":-13.2474794},"Timestamp":"2022-07-13T10:19:32.530149-04:00"},"4":{"Id":"4","Root":{"X":-1.4562397,"Y":10.0533276,"Z":-13.2474794},"Timestamp":"2022-07-13T10:19:34.100216-04:00"},"5":{"Id":"5","Root":{"X":-1.4562397,"Y":10.0533276,"Z":-13.2474794},"Timestamp":"2022-07-13T10:19:35.242144-04:00"},"6":{"Id":"6","Root":{"X":-1.4562397,"Y":10.0533276,"Z":-13.2474794},"Timestamp":"2022-07-13T10:19:35.589787-04:00"},"7":{"Id":"7","Root":{"X":-1.4562397,"Y":10.0533276,"Z":-13.2474794},"Timestamp":"2022-07-13T10:19:36.117958-04:00"},"8":{"Id":"8","Root":{"X":-1.4562397,"Y":10.0533276,"Z":-13.2474794},"Timestamp":"2022-07-13T10:19:36.772519-04:00"},"9":{"Id":"9","Root":{"X":-1.4562397,"Y":10.0533276,"Z":-13.2474794},"Timestamp":"2022-07-13T10:19:46.382024-04:00"},"10":{"Id":"10","Root":{"X":-1.4562397,"Y":10.0533276,"Z":-13.2474794},"Timestamp":"2022-07-13T10:19:46.714364-04:00"},"11":{"Id":"11","Root":{"X":-1.4562397,"Y":10.0533276,"Z":-13.2474794},"Timestamp":"2022-07-13T10:19:48.276116-04:00"},"12":{"Id":"12","Root":{"X":-1.4520874,"Y":11.519,"Z":-13.307251},"Timestamp":"2022-07-13T10:19:48.662393-04:00"},"13":{"Id":"13","Root":{"X":-1.4562397,"Y":10.0533276,"Z":-13.2474794},"Timestamp":"2022-07-13T10:19:52.26884-04:00"},"14":{"Id":"14","Root":{"X":-1.4562397,"Y":10.0533276,"Z":-13.2474794},"Timestamp":"2022-07-13T10:19:53.883977-04:00"},"15":{"Id":"15","Root":{"X":-1.4562397,"Y":10.0533276,"Z":-13.2474794},"Timestamp":"2022-07-13T10:19:54.63564-04:00"},"16":{"Id":"16","Root":{"X":-1.4562397,"Y":10.0533276,"Z":-13.2474794},"Timestamp":"2022-07-13T10:19:55.88902-04:00"},"17":{"Id":"17","Root":{"X":-1.4562397,"Y":10.0533276,"Z":-13.2474794},"Timestamp":"2022-07-13T10:19:56.613013-04:00"},"18":{"Id":"18","Root":{"X":-1.4562397,"Y":10.0533276,"Z":-13.2474794},"Timestamp":"2022-07-13T10:20:02.557265-04:00"},"19":{"Id":"19","Root":{"X":-1.4562397,"Y":10.0533276,"Z":-13.2474794},"Timestamp":"2022-07-13T10:20:04.033833-04:00"},"20":{"Id":"20","Root":{"X":-1.4520874,"Y":11.519,"Z":-25.289},"Timestamp":"2022-07-13T10:20:05.383737-04:00"},"21":{"Id":"21","Root":{"X":-2.74,"Y":1.519,"Z":0.0},"Timestamp":"2022-07-13T10:21:05.307446-04:00"},"22":{"Id":"22","Root":{"X":-2.74,"Y":1.519,"Z":0.0},"Timestamp":"2022-07-13T10:22:54.653125-04:00"},"23":{"Id":"23","Root":{"X":-2.74,"Y":1.519,"Z":0.0},"Timestamp":"2022-07-13T10:24:05.948789-04:00"},"24":{"Id":"24","Root":{"X":-43.094,"Y":3.843,"Z":-38.453},"Timestamp":"2022-07-13T10:25:01.483457-04:00"},"25":{"Id":"25","Root":{"X":31.37,"Y":4.199,"Z":-52.42},"Timestamp":"2022-07-13T10:27:22.651865-04:00"}},"Decisions":{"0":{"Id":"0","Timestamp":"2022-07-13T10:23:25.828724-04:00","DecisionValue":"Leatherback","CorrectValue":"Hawksbill","TaskId":"Turtle Guessing"},"1":{"Id":"1","Timestamp":"2022-07-13T10:23:34.02465-04:00","DecisionValue":"Loggerhead","CorrectValue":"Hawksbill","TaskId":"Turtle Guessing"},"2":{"Id":"2","Timestamp":"2022-07-13T10:23:35.235716-04:00","DecisionValue":"Leatherback","CorrectValue":"Hawksbill","TaskId":"Turtle Guessing"},"3":{"Id":"3","Timestamp":"2022-07-13T10:23:37.505425-04:00","DecisionValue":"Hawksbill","CorrectValue":"Hawksbill","TaskId":"Turtle Guessing"},"4":{"Id":"4","Timestamp":"2022-07-13T10:23:50.313632-04:00","DecisionValue":"Loggerhead","CorrectValue":"Leatherback","TaskId":"Turtle Guessing"},"5":{"Id":"5","Timestamp":"2022-07-13T10:23:50.730915-04:00","DecisionValue":"Loggerhead","CorrectValue":"Leatherback","TaskId":"Turtle Guessing"},"6":{"Id":"6","Timestamp":"2022-07-13T10:23:51.385993-04:00","DecisionValue":"Leatherback","CorrectValue":"Leatherback","TaskId":"Turtle Guessing"},"7":{"Id":"7","Timestamp":"2022-07-13T10:23:53.725257-04:00","DecisionValue":"Loggerhead","CorrectValue":"Loggerhead","TaskId":"Turtle Guessing"},"8":{"Id":"8","Timestamp":"2022-07-13T10:24:03.456047-04:00","DecisionValue":"Loggerhead","CorrectValue":"Loggerhead","TaskId":"Turtle Guessing"},"9":{"Id":"9","Timestamp":"2022-07-13T10:24:22.334734-04:00","DecisionValue":"Load First Track","CorrectValue":null,"TaskId":"Track Guessing"},"10":{"Id":"10","Timestamp":"2022-07-13T10:24:31.258791-04:00","DecisionValue":"Loggerhead","CorrectValue":"Green","TaskId":"Track Guessing"},"11":{"Id":"11","Timestamp":"2022-07-13T10:24:32.024766-04:00","DecisionValue":"Leatherback","CorrectValue":"Green","TaskId":"Track Guessing"},"12":{"Id":"12","Timestamp":"2022-07-13T10:24:32.845919-04:00","DecisionValue":"Green","CorrectValue":"Green","TaskId":"Track Guessing"},"13":{"Id":"13","Timestamp":"2022-07-13T10:24:33.291258-04:00","DecisionValue":"Green","CorrectValue":"Leatherback","TaskId":"Track Guessing"},"14":{"Id":"14","Timestamp":"2022-07-13T10:24:42.173732-04:00","DecisionValue":"Leatherback","CorrectValue":"Leatherback","TaskId":"Track Guessing"},"15":{"Id":"15","Timestamp":"2022-07-13T10:24:45.878241-04:00","DecisionValue":"Green","CorrectValue":"Loggerhead","TaskId":"Track Guessing"},"16":{"Id":"16","Timestamp":"2022-07-13T10:24:47.158656-04:00","DecisionValue":"Loggerhead","CorrectValue":"Loggerhead","TaskId":"Track Guessing"}},"Interactions":{"0":{"Id":"0","Timestamp":"2022-07-13T10:19:51.043522-04:00","WasPickedUp":true,"Name":"Beachball 2"},"2":{"Id":"2","Timestamp":"2022-07-13T10:19:51.55999-04:00","WasPickedUp":true,"Name":"Beachball 2"},"4":{"Id":"4","Timestamp":"2022-07-13T10:19:51.739167-04:00","WasPickedUp":true,"Name":"Beachball 2"},"6":{"Id":"6","Timestamp":"2022-07-13T10:19:53.326859-04:00","WasPickedUp":true,"Name":"Beachball 2"},"8":{"Id":"8","Timestamp":"2022-07-13T10:19:53.340256-04:00","WasPickedUp":true,"Name":"Beachball 2"},"10":{"Id":"10","Timestamp":"2022-07-13T10:19:54.217328-04:00","WasPickedUp":true,"Name":"Beachball 2"},"12":{"Id":"12","Timestamp":"2022-07-13T10:19:54.218683-04:00","WasPickedUp":true,"Name":"Beachball 2"},"14":{"Id":"14","Timestamp":"2022-07-13T10:19:54.844196-04:00","WasPickedUp":true,"Name":"Beachball 2"},"16":{"Id":"16","Timestamp":"2022-07-13T10:19:56.45944-04:00","WasPickedUp":true,"Name":"Beachball 2"},"18":{"Id":"18","Timestamp":"2022-07-13T10:20:26.295619-04:00","WasPickedUp":true,"Name":"Tool Table Calipers"},"20":{"Id":"20","Timestamp":"2022-07-13T10:20:26.730821-04:00","WasPickedUp":true,"Name":"Tool Table Calipers"},"22":{"Id":"22","Timestamp":"2022-07-13T10:20:26.742209-04:00","WasPickedUp":true,"Name":"Tool Table Calipers"},"24":{"Id":"24","Timestamp":"2022-07-13T10:20:27.215574-04:00","WasPickedUp":true,"Name":"Tool Table Calipers"},"26":{"Id":"26","Timestamp":"2022-07-13T10:20:35.26228-04:00","WasPickedUp":true,"Name":"Tool Table Calipers"},"28":{"Id":"28","Timestamp":"2022-07-13T10:20:35.707357-04:00","WasPickedUp":true,"Name":"Tool Table Calipers"},"30":{"Id":"30","Timestamp":"2022-07-13T10:20:41.707883-04:00","WasPickedUp":true,"Name":"Tool Table Calipers"},"32":{"Id":"32","Timestamp":"2022-07-13T10:20:42.125555-04:00","WasPickedUp":true,"Name":"Tool Table Calipers"},"34":{"Id":"34","Timestamp":"2022-07-13T10:20:42.127222-04:00","WasPickedUp":true,"Name":"Tool Table Calipers"},"36":{"Id":"36","Timestamp":"2022-07-13T10:20:46.179801-04:00","WasPickedUp":true,"Name":"Tool Table Calipers"},"38":{"Id":"38","Timestamp":"2022-07-13T10:20:50.578844-04:00","WasPickedUp":true,"Name":"Tool Table Tape Measure"},"40":{"Id":"40","Timestamp":"2022-07-13T10:20:50.771493-04:00","WasPickedUp":true,"Name":"Tool Table Tape Measure"},"42":{"Id":"42","Timestamp":"2022-07-13T10:20:54.547552-04:00","WasPickedUp":true,"Name":"Tool Table Tape Measure"},"44":{"Id":"44","Timestamp":"2022-07-13T10:20:55.143705-04:00","WasPickedUp":true,"Name":"Tool Table Tape Measure"},"46":{"Id":"46","Timestamp":"2022-07-13T10:20:55.853305-04:00","WasPickedUp":true,"Name":"Tool Table Tape Measure"},"48":{"Id":"48","Timestamp":"2022-07-13T10:20:56.423708-04:00","WasPickedUp":true,"Name":"Tool Table Tape Measure"},"50":{"Id":"50","Timestamp":"2022-07-13T10:21:01.589368-04:00","WasPickedUp":true,"Name":"Tool Table Tape Measure"},"52":{"Id":"52","Timestamp":"2022-07-13T10:21:15.472583-04:00","WasPickedUp":true,"Name":"Calipers"},"54":{"Id":"54","Timestamp":"2022-07-13T10:21:15.90009-04:00","WasPickedUp":true,"Name":"Calipers"},"56":{"Id":"56","Timestamp":"2022-07-13T10:21:16.402584-04:00","WasPickedUp":true,"Name":"Calipers"},"58":{"Id":"58","Timestamp":"2022-07-13T10:21:16.430051-04:00","WasPickedUp":true,"Name":"Calipers"},"60":{"Id":"60","Timestamp":"2022-07-13T10:21:22.542627-04:00","WasPickedUp":true,"Name":"Tape Measure"},"62":{"Id":"62","Timestamp":"2022-07-13T10:21:57.682737-04:00","WasPickedUp":true,"Name":"Calipers"},"64":{"Id":"64","Timestamp":"2022-07-13T10:22:02.764633-04:00","WasPickedUp":true,"Name":"Calipers"},"66":{"Id":"66","Timestamp":"2022-07-13T10:22:04.099688-04:00","WasPickedUp":true,"Name":"Calipers"},"68":{"Id":"68","Timestamp":"2022-07-13T10:22:06.188771-04:00","WasPickedUp":true,"Name":"Calipers"},"70":{"Id":"70","Timestamp":"2022-07-13T10:22:19.442766-04:00","WasPickedUp":true,"Name":"Calipers"},"72":{"Id":"72","Timestamp":"2022-07-13T10:22:19.87458-04:00","WasPickedUp":true,"Name":"Calipers"},"74":{"Id":"74","Timestamp":"2022-07-13T10:22:30.483708-04:00","WasPickedUp":true,"Name":"Tape Measure"},"76":{"Id":"76","Timestamp":"2022-07-13T10:22:31.346881-04:00","WasPickedUp":true,"Name":"Tape Measure"},"78":{"Id":"78","Timestamp":"2022-07-13T10:22:37.193586-04:00","WasPickedUp":true,"Name":"Tape Measure"},"80":{"Id":"80","Timestamp":"2022-07-13T10:22:37.666604-04:00","WasPickedUp":true,"Name":"Tape Measure"},"82":{"Id":"82","Timestamp":"2022-07-13T10:25:08.122817-04:00","WasPickedUp":true,"Name":"GloveR"},"84":{"Id":"84","Timestamp":"2022-07-13T10:25:50.381439-04:00","WasPickedUp":true,"Name":"Egg4"},"86":{"Id":"86","Timestamp":"2022-07-13T10:25:58.080805-04:00","WasPickedUp":true,"Name":"Egg2"},"88":{"Id":"88","Timestamp":"2022-07-13T10:26:03.955485-04:00","WasPickedUp":true,"Name":"Egg1"},"90":{"Id":"90","Timestamp":"2022-07-13T10:26:09.74775-04:00","WasPickedUp":true,"Name":"Egg3"},"92":{"Id":"92","Timestamp":"2022-07-13T10:26:15.539268-04:00","WasPickedUp":true,"Name":"Egg6"},"94":{"Id":"94","Timestamp":"2022-07-13T10:26:20.049566-04:00","WasPickedUp":true,"Name":"Egg5"},"96":{"Id":"96","Timestamp":"2022-07-13T10:26:24.227868-04:00","WasPickedUp":true,"Name":"Egg4"},"98":{"Id":"98","Timestamp":"2022-07-13T10:26:28.583316-04:00","WasPickedUp":true,"Name":"CrackedEgg1"},"100":{"Id":"100","Timestamp":"2022-07-13T10:26:32.635351-04:00","WasPickedUp":true,"Name":"CrackedEgg2"},"102":{"Id":"102","Timestamp":"2022-07-13T10:26:37.758277-04:00","WasPickedUp":true,"Name":"HalfEgg1"},"104":{"Id":"104","Timestamp":"2022-07-13T10:26:38.231987-04:00","WasPickedUp":true,"Name":"HalfEgg1"},"106":{"Id":"106","Timestamp":"2022-07-13T10:26:42.687468-04:00","WasPickedUp":true,"Name":"HalfEgg2"},"108":{"Id":"108","Timestamp":"2022-07-13T10:26:46.209575-04:00","WasPickedUp":true,"Name":"HalfEgg1"},"110":{"Id":"110","Timestamp":"2022-07-13T10:26:55.384129-04:00","WasPickedUp":true,"Name":"Egg5"},"112":{"Id":"112","Timestamp":"2022-07-13T10:27:33.350495-04:00","WasPickedUp":true,"Name":"GoodEgg1"},"114":{"Id":"114","Timestamp":"2022-07-13T10:27:36.845318-04:00","WasPickedUp":true,"Name":"GoodEgg6"},"116":{"Id":"116","Timestamp":"2022-07-13T10:27:43.263534-04:00","WasPickedUp":true,"Name":"GoodEgg5"},"118":{"Id":"118","Timestamp":"2022-07-13T10:28:46.554774-04:00","WasPickedUp":true,"Name":"GoodEgg4"},"120":{"Id":"120","Timestamp":"2022-07-13T10:28:53.571098-04:00","WasPickedUp":true,"Name":"GoodEgg1"},"122":{"Id":"122","Timestamp":"2022-07-13T10:29:02.133485-04:00","WasPickedUp":true,"Name":"GoodEgg2"},"124":{"Id":"124","Timestamp":"2022-07-13T10:29:03.693065-04:00","WasPickedUp":true,"Name":"GoodEgg3"},"126":{"Id":"126","Timestamp":"2022-07-13T10:29:04.769466-04:00","WasPickedUp":true,"Name":"GoodEgg3"},"128":{"Id":"128","Timestamp":"2022-07-13T10:29:16.891242-04:00","WasPickedUp":true,"Name":"GoodEgg1"},"130":{"Id":"130","Timestamp":"2022-07-13T10:30:54.529002-04:00","WasPickedUp":true,"Name":"GoodEgg3"},"132":{"Id":"132","Timestamp":"2022-07-13T10:30:55.307747-04:00","WasPickedUp":true,"Name":"GoodEgg1"},"134":{"Id":"134","Timestamp":"2022-07-13T10:30:56.521458-04:00","WasPickedUp":true,"Name":"GoodEgg1"},"136":{"Id":"136","Timestamp":"2022-07-13T10:30:57.621346-04:00","WasPickedUp":true,"Name":"GoodEgg1"},"138":{"Id":"138","Timestamp":"2022-07-13T10:30:58.4287-04:00","WasPickedUp":true,"Name":"GoodEgg1"},"140":{"Id":"140","Timestamp":"2022-07-13T10:31:26.3984-04:00","WasPickedUp":true,"Name":"GoodEgg4"},"142":{"Id":"142","Timestamp":"2022-07-13T10:31:26.452689-04:00","WasPickedUp":true,"Name":"GoodEgg4"},"144":{"Id":"144","Timestamp":"2022-07-13T10:31:33.74813-04:00","WasPickedUp":true,"Name":"GoodEgg6"},"146":{"Id":"146","Timestamp":"2022-07-13T10:31:35.154032-04:00","WasPickedUp":true,"Name":"GoodEgg4"},"148":{"Id":"148","Timestamp":"2022-07-13T10:31:38.569606-04:00","WasPickedUp":true,"Name":"GoodEgg4"},"150":{"Id":"150","Timestamp":"2022-07-13T10:31:39.292948-04:00","WasPickedUp":true,"Name":"GoodEgg4"},"152":{"Id":"152","Timestamp":"2022-07-13T10:31:45.123785-04:00","WasPickedUp":true,"Name":"GoodEgg2"},"154":{"Id":"154","Timestamp":"2022-07-13T10:31:46.57168-04:00","WasPickedUp":true,"Name":"GoodEgg5"},"156":{"Id":"156","Timestamp":"2022-07-13T10:31:48.622941-04:00","WasPickedUp":true,"Name":"GoodEgg2"},"158":{"Id":"158","Timestamp":"2022-07-13T10:31:49.526571-04:00","WasPickedUp":true,"Name":"GoodEgg2"},"160":{"Id":"160","Timestamp":"2022-07-13T10:32:03.535584-04:00","WasPickedUp":true,"Name":"Shovel"},"162":{"Id":"162","Timestamp":"2022-07-13T10:32:03.698325-04:00","WasPickedUp":true,"Name":"Shovel"},"164":{"Id":"164","Timestamp":"2022-07-13T10:32:06.865004-04:00","WasPickedUp":true,"Name":"Shovel"},"166":{"Id":"166","Timestamp":"2022-07-13T10:32:08.744394-04:00","WasPickedUp":true,"Name":"Shovel"},"168":{"Id":"168","Timestamp":"2022-07-13T10:32:09.647668-04:00","WasPickedUp":true,"Name":"Shovel"},"170":{"Id":"170","Timestamp":"2022-07-13T10:32:11.872393-04:00","WasPickedUp":true,"Name":"Shovel"},"172":{"Id":"172","Timestamp":"2022-07-13T10:32:17.711394-04:00","WasPickedUp":true,"Name":"Shovel"},"174":{"Id":"174","Timestamp":"2022-07-13T10:32:18.343113-04:00","WasPickedUp":true,"Name":"Shovel"},"176":{"Id":"176","Timestamp":"2022-07-13T10:33:25.307149-04:00","WasPickedUp":true,"Name":"Cage"},"178":{"Id":"178","Timestamp":"2022-07-13T10:33:25.309965-04:00","WasPickedUp":true,"Name":"Cage"},"180":{"Id":"180","Timestamp":"2022-07-13T10:33:25.742783-04:00","WasPickedUp":true,"Name":"Cage"},"182":{"Id":"182","Timestamp":"2022-07-13T10:33:27.763598-04:00","WasPickedUp":true,"Name":"Cage"},"184":{"Id":"184","Timestamp":"2022-07-13T10:33:28.236866-04:00","WasPickedUp":true,"Name":"Cage"},"186":{"Id":"186","Timestamp":"2022-07-13T10:33:28.666603-04:00","WasPickedUp":true,"Name":"Cage"},"188":{"Id":"188","Timestamp":"2022-07-13T10:33:50.698611-04:00","WasPickedUp":true,"Name":"Sign"},"190":{"Id":"190","Timestamp":"2022-07-13T10:33:50.837574-04:00","WasPickedUp":true,"Name":"Sign"}},"Activities":{"0":{"Id":"0","Timestamp":"2022-07-13T10:19:22.644135-04:00","ActivityDetail":"Completed first Teleport"},"1":{"Id":"1","Timestamp":"2022-07-13T10:19:26.413923-04:00","ActivityDetail":"Completed first Snap Turn"},"2":{"Id":"2","Timestamp":"2022-07-13T10:19:51.558837-04:00","ActivityDetail":"Completed first Object Grab"},"3":{"Id":"3","Timestamp":"2022-07-13T10:20:07.931404-04:00","ActivityDetail":"Completed first Button Click"},"4":{"Id":"4","Timestamp":"2022-07-13T10:20:26.729392-04:00","ActivityDetail":"First Caliper Pick-Up"},"5":{"Id":"5","Timestamp":"2022-07-13T10:20:31.183251-04:00","ActivityDetail":"Completed caliper testing"},"6":{"Id":"6","Timestamp":"2022-07-13T10:20:47.95918-04:00","ActivityDetail":"Measured Jar with Calipers"},"7":{"Id":"7","Timestamp":"2022-07-13T10:20:50.577145-04:00","ActivityDetail":"Tape Measure Picked-up"},"8":{"Id":"8","Timestamp":"2022-07-13T10:21:03.134273-04:00","ActivityDetail":"Measured Clipboard with Tape Measure"},"9":{"Id":"9","Timestamp":"2022-07-13T10:21:20.662474-04:00","ActivityDetail":"Successfully Measured the Front Fin"},"10":{"Id":"10","Timestamp":"2022-07-13T10:22:20.987843-04:00","ActivityDetail":"Successfully Measured the Back Fin"},"11":{"Id":"11","Timestamp":"2022-07-13T10:22:40.2292-04:00","ActivityDetail":"Successfully Measured the Shell Length"},"12":{"Id":"12","Timestamp":"2022-07-13T10:22:50.698213-04:00","ActivityDetail":"Successfully measured the Shell Width"},"13":{"Id":"13","Timestamp":"2022-07-13T10:23:53.934846-04:00","ActivityDetail":"Completed Turtle Identification Table"},"14":{"Id":"14","Timestamp":"2022-07-13T10:24:47.451358-04:00","ActivityDetail":"Completed Track Identification Table"},"15":{"Id":"15","Timestamp":"2022-07-13T10:25:01.48118-04:00","ActivityDetail":"Entered excavation waypoint"},"16":{"Id":"16","Timestamp":"2022-07-13T10:25:08.120573-04:00","ActivityDetail":"Put on Gloves"},"17":{"Id":"17","Timestamp":"2022-07-13T10:25:15.576107-04:00","ActivityDetail":"Dug up the nest"},"18":{"Id":"18","Timestamp":"2022-07-13T10:26:57.434248-04:00","ActivityDetail":"Finished sorting eggs"},"19":{"Id":"19","Timestamp":"2022-07-13T10:27:22.648364-04:00","ActivityDetail":"Entered relocation waypoint"},"20":{"Id":"20","Timestamp":"2022-07-13T10:31:51.752453-04:00","ActivityDetail":"Successfully placed eggs in the new nest"},"21":{"Id":"21","Timestamp":"2022-07-13T10:32:03.532344-04:00","ActivityDetail":"Grabbed shovel"},"22":{"Id":"22","Timestamp":"2022-07-13T10:32:12.502256-04:00","ActivityDetail":"Covered nest with sand"},"23":{"Id":"23","Timestamp":"2022-07-13T10:33:25.303861-04:00","ActivityDetail":"Cage grabbed"},"24":{"Id":"24","Timestamp":"2022-07-13T10:33:30.711965-04:00","ActivityDetail":"Cage placed"},"25":{"Id":"25","Timestamp":"2022-07-13T10:33:50.694845-04:00","ActivityDetail":"Sign grabbed"},"26":{"Id":"26","Timestamp":"2022-07-13T10:33:55.787147-04:00","ActivityDetail":"Sign placed"}}}