{"SessionScene":"Module_01","Id":"23","StartTime":"2022-07-21T18:04:55.897997Z","EndTime":"2022-07-21T18:13:08.165223Z","Student":{"Id":"0","FirstName":"TrustWorthy Squid","LastName":"","Sessions":{}},"Movements":{"0":{"Id":"0","Root":{"X":-0.6461487,"Y":0.00608587265,"Z":0.7883773},"Timestamp":"2022-07-21T14:06:56.782755-04:00"},"1":{"Id":"1","Root":{"X":0.239851,"Y":0.0150856972,"Z":0.7883773},"Timestamp":"2022-07-21T14:07:02.560131-04:00"},"2":{"Id":"2","Root":{"X":0.239851,"Y":0.0150856972,"Z":0.7883773},"Timestamp":"2022-07-21T14:07:51.678167-04:00"},"3":{"Id":"3","Root":{"X":0.239851,"Y":0.0150856972,"Z":0.7883773},"Timestamp":"2022-07-21T14:07:52.30492-04:00"},"4":{"Id":"4","Root":{"X":-2.74,"Y":1.519,"Z":0.0},"Timestamp":"2022-07-21T14:09:37.503824-04:00"},"5":{"Id":"5","Root":{"X":0.239851,"Y":0.0150856972,"Z":0.7883773},"Timestamp":"2022-07-21T14:11:14.219974-04:00"},"6":{"Id":"6","Root":{"X":-2.74,"Y":1.519,"Z":0.0},"Timestamp":"2022-07-21T14:11:21.85059-04:00"},"7":{"Id":"7","Root":{"X":-2.739149,"Y":0.03708601,"Z":-0.0156230927},"Timestamp":"2022-07-21T14:11:24.926567-04:00"},"8":{"Id":"8","Root":{"X":-2.739149,"Y":0.03708601,"Z":-0.0156230927},"Timestamp":"2022-07-21T14:11:25.455601-04:00"},"9":{"Id":"9","Root":{"X":-0.6461487,"Y":0.00608587265,"Z":0.7883773},"Timestamp":"2022-07-21T14:11:29.925046-04:00"},"10":{"Id":"10","Root":{"X":-2.74,"Y":1.519,"Z":0.0},"Timestamp":"2022-07-21T14:12:20.077365-04:00"},"11":{"Id":"11","Root":{"X":-0.6461487,"Y":0.00608587265,"Z":0.7883773},"Timestamp":"2022-07-21T14:12:55.74913-04:00"}},"Decisions":{"0":{"Id":"0","Timestamp":"2022-07-21T14:11:55.200088-04:00","DecisionValue":"Leatherback","CorrectValue":"Loggerhead","TaskId":"Turtle Guessing"},"1":{"Id":"1","Timestamp":"2022-07-21T14:12:03.426496-04:00","DecisionValue":"Loggerhead","CorrectValue":"Loggerhead","TaskId":"Turtle Guessing"},"2":{"Id":"2","Timestamp":"2022-07-21T14:12:08.326828-04:00","DecisionValue":"Leatherback","CorrectValue":"Leatherback","TaskId":"Turtle Guessing"},"3":{"Id":"3","Timestamp":"2022-07-21T14:12:08.5906-04:00","DecisionValue":"Leatherback","CorrectValue":"Hawksbill","TaskId":"Turtle Guessing"},"4":{"Id":"4","Timestamp":"2022-07-21T14:12:12.085884-04:00","DecisionValue":"Hawksbill","CorrectValue":"Hawksbill","TaskId":"Turtle Guessing"},"5":{"Id":"5","Timestamp":"2022-07-21T14:12:21.774889-04:00","DecisionValue":"Load First Track","CorrectValue":null,"TaskId":"Track Guessing"},"6":{"Id":"6","Timestamp":"2022-07-21T14:12:34.236098-04:00","DecisionValue":"Green","CorrectValue":"Loggerhead","TaskId":"Track Guessing"},"7":{"Id":"7","Timestamp":"2022-07-21T14:12:37.952722-04:00","DecisionValue":"Loggerhead","CorrectValue":"Loggerhead","TaskId":"Track Guessing"},"8":{"Id":"8","Timestamp":"2022-07-21T14:12:44.231254-04:00","DecisionValue":"Green","CorrectValue":"Green","TaskId":"Track Guessing"},"9":{"Id":"9","Timestamp":"2022-07-21T14:12:57.486595-04:00","DecisionValue":"Leatherback","CorrectValue":"Leatherback","TaskId":"Track Guessing"}},"Interactions":{"0":{"Id":"0","Timestamp":"2022-07-21T14:05:17.976158-04:00","WasPickedUp":true,"Name":"Tool Table Calipers"},"2":{"Id":"2","Timestamp":"2022-07-21T14:05:20.092029-04:00","WasPickedUp":true,"Name":"Tool Table Calipers"},"4":{"Id":"4","Timestamp":"2022-07-21T14:05:20.109156-04:00","WasPickedUp":true,"Name":"Tool Table Calipers"},"6":{"Id":"6","Timestamp":"2022-07-21T14:05:21.233595-04:00","WasPickedUp":true,"Name":"Tool Table Calipers"},"8":{"Id":"8","Timestamp":"2022-07-21T14:05:23.795353-04:00","WasPickedUp":true,"Name":"Tool Table Calipers"},"10":{"Id":"10","Timestamp":"2022-07-21T14:05:26.483102-04:00","WasPickedUp":true,"Name":"Tool Table Calipers"},"12":{"Id":"12","Timestamp":"2022-07-21T14:05:27.123155-04:00","WasPickedUp":true,"Name":"Tool Table Calipers"},"14":{"Id":"14","Timestamp":"2022-07-21T14:05:28.124724-04:00","WasPickedUp":true,"Name":"Tool Table Calipers"},"16":{"Id":"16","Timestamp":"2022-07-21T14:05:28.167855-04:00","WasPickedUp":true,"Name":"Tool Table Calipers"},"18":{"Id":"18","Timestamp":"2022-07-21T14:05:47.296454-04:00","WasPickedUp":true,"Name":"Tool Table Calipers"},"20":{"Id":"20","Timestamp":"2022-07-21T14:05:47.936899-04:00","WasPickedUp":true,"Name":"Tool Table Calipers"},"22":{"Id":"22","Timestamp":"2022-07-21T14:06:13.582192-04:00","WasPickedUp":true,"Name":"Tool Table Calipers"},"24":{"Id":"24","Timestamp":"2022-07-21T14:06:13.929841-04:00","WasPickedUp":true,"Name":"Tool Table Calipers"},"26":{"Id":"26","Timestamp":"2022-07-21T14:06:14.444938-04:00","WasPickedUp":true,"Name":"Tool Table Calipers"},"28":{"Id":"28","Timestamp":"2022-07-21T14:06:20.723339-04:00","WasPickedUp":true,"Name":"Tool Table Calipers"},"30":{"Id":"30","Timestamp":"2022-07-21T14:06:22.853519-04:00","WasPickedUp":true,"Name":"Tool Table Calipers"},"32":{"Id":"32","Timestamp":"2022-07-21T14:06:34.38248-04:00","WasPickedUp":true,"Name":"Tool Table Calipers"},"34":{"Id":"34","Timestamp":"2022-07-21T14:06:40.898008-04:00","WasPickedUp":true,"Name":"Tool Table Calipers"},"36":{"Id":"36","Timestamp":"2022-07-21T14:06:49.084065-04:00","WasPickedUp":true,"Name":"Tool Table Calipers"},"38":{"Id":"38","Timestamp":"2022-07-21T14:06:49.390161-04:00","WasPickedUp":true,"Name":"Tool Table Calipers"},"40":{"Id":"40","Timestamp":"2022-07-21T14:06:49.710477-04:00","WasPickedUp":true,"Name":"Tool Table Calipers"},"42":{"Id":"42","Timestamp":"2022-07-21T14:07:03.744058-04:00","WasPickedUp":true,"Name":"Tool Table Calipers"},"44":{"Id":"44","Timestamp":"2022-07-21T14:07:10.593173-04:00","WasPickedUp":true,"Name":"Tool Table Calipers"},"46":{"Id":"46","Timestamp":"2022-07-21T14:07:20.924143-04:00","WasPickedUp":true,"Name":"Tool Table Calipers"},"48":{"Id":"48","Timestamp":"2022-07-21T14:07:21.828729-04:00","WasPickedUp":true,"Name":"Tool Table Calipers"},"50":{"Id":"50","Timestamp":"2022-07-21T14:07:26.382139-04:00","WasPickedUp":true,"Name":"Tool Table Calipers"},"52":{"Id":"52","Timestamp":"2022-07-21T14:07:29.471766-04:00","WasPickedUp":true,"Name":"Tool Table Calipers"},"54":{"Id":"54","Timestamp":"2022-07-21T14:07:31.588641-04:00","WasPickedUp":true,"Name":"Tool Table Calipers"},"56":{"Id":"56","Timestamp":"2022-07-21T14:07:32.368362-04:00","WasPickedUp":true,"Name":"Tool Table Calipers"},"58":{"Id":"58","Timestamp":"2022-07-21T14:08:07.270952-04:00","WasPickedUp":true,"Name":"Tool Table Calipers"},"60":{"Id":"60","Timestamp":"2022-07-21T14:08:08.204679-04:00","WasPickedUp":true,"Name":"Tool Table Calipers"},"62":{"Id":"62","Timestamp":"2022-07-21T14:08:35.146263-04:00","WasPickedUp":true,"Name":"Tool Table Tape Measure"},"64":{"Id":"64","Timestamp":"2022-07-21T14:08:49.442318-04:00","WasPickedUp":true,"Name":"Tool Table Tape Measure"},"66":{"Id":"66","Timestamp":"2022-07-21T14:08:56.222217-04:00","WasPickedUp":true,"Name":"Tool Table Tape Measure"},"68":{"Id":"68","Timestamp":"2022-07-21T14:08:56.264433-04:00","WasPickedUp":true,"Name":"Tool Table Tape Measure"},"70":{"Id":"70","Timestamp":"2022-07-21T14:09:29.942143-04:00","WasPickedUp":true,"Name":"Tool Table Calipers"},"72":{"Id":"72","Timestamp":"2022-07-21T14:09:37.505384-04:00","WasPickedUp":true,"Name":"Tool Table Calipers"},"74":{"Id":"74","Timestamp":"2022-07-21T14:09:59.527426-04:00","WasPickedUp":true,"Name":"Calipers"},"76":{"Id":"76","Timestamp":"2022-07-21T14:10:22.915546-04:00","WasPickedUp":true,"Name":"Calipers"},"78":{"Id":"78","Timestamp":"2022-07-21T14:10:33.34799-04:00","WasPickedUp":true,"Name":"Tape Measure"},"80":{"Id":"80","Timestamp":"2022-07-21T14:10:44.07861-04:00","WasPickedUp":true,"Name":"Tape Measure"},"82":{"Id":"82","Timestamp":"2022-07-21T14:10:53.546238-04:00","WasPickedUp":true,"Name":"Tape Measure"},"84":{"Id":"84","Timestamp":"2022-07-21T14:10:59.267791-04:00","WasPickedUp":true,"Name":"Tape Measure"},"86":{"Id":"86","Timestamp":"2022-07-21T14:11:00.925001-04:00","WasPickedUp":true,"Name":"Tape Measure"}},"Activities":{"0":{"Id":"0","Timestamp":"2022-07-21T14:05:20.108426-04:00","ActivityDetail":"First Caliper Pick-Up"},"1":{"Id":"1","Timestamp":"2022-07-21T14:08:17.587811-04:00","ActivityDetail":"Completed caliper testing"},"2":{"Id":"2","Timestamp":"2022-07-21T14:08:23.227158-04:00","ActivityDetail":"Measured Jar with Calipers"},"3":{"Id":"3","Timestamp":"2022-07-21T14:08:35.14491-04:00","ActivityDetail":"Tape Measure Picked-up"},"4":{"Id":"4","Timestamp":"2022-07-21T14:09:01.443352-04:00","ActivityDetail":"Measured Clipboard with Tape Measure"},"5":{"Id":"5","Timestamp":"2022-07-21T14:10:13.911832-04:00","ActivityDetail":"Successfully Measured the Front Fin"},"6":{"Id":"6","Timestamp":"2022-07-21T14:10:24.922538-04:00","ActivityDetail":"Successfully Measured the Back Fin"},"7":{"Id":"7","Timestamp":"2022-07-21T14:10:39.610514-04:00","ActivityDetail":"Successfully Measured the Shell Length"},"8":{"Id":"8","Timestamp":"2022-07-21T14:11:04.614481-04:00","ActivityDetail":"Successfully measured the Shell Width"},"9":{"Id":"9","Timestamp":"2022-07-21T14:12:12.365689-04:00","ActivityDetail":"Completed Turtle Identification Table"},"10":{"Id":"10","Timestamp":"2022-07-21T14:12:58.141298-04:00","ActivityDetail":"Completed Track Identification Table"}}}