{"SessionScene":"Module_01","Id":"32","StartTime":"2022-07-21T17:57:44.354303Z","EndTime":null,"Student":{"Id":"0","FirstName":"Awesome Barracuda","LastName":"","Sessions":{}},"Movements":{"15":{"Id":"15","Root":{"X":-2.739149,"Y":0.03708601,"Z":-0.0156230927},"Timestamp":"2022-07-21T13:58:21.093359-04:00"},"16":{"Id":"16","Root":{"X":-0.6461487,"Y":0.00608587265,"Z":0.7883773},"Timestamp":"2022-07-21T13:59:24.286788-04:00"},"17":{"Id":"17","Root":{"X":-2.739149,"Y":0.03708601,"Z":-0.0156230927},"Timestamp":"2022-07-21T14:00:17.620221-04:00"},"18":{"Id":"18","Root":{"X":-0.6461487,"Y":0.00608587265,"Z":0.7883773},"Timestamp":"2022-07-21T14:00:26.265909-04:00"},"19":{"Id":"19","Root":{"X":0.239851,"Y":0.0150856972,"Z":0.7883773},"Timestamp":"2022-07-21T14:00:31.361124-04:00"},"20":{"Id":"20","Root":{"X":0.239851,"Y":0.0150856972,"Z":0.7883773},"Timestamp":"2022-07-21T14:01:20.646462-04:00"},"21":{"Id":"21","Root":{"X":0.239851,"Y":0.0150856972,"Z":0.7883773},"Timestamp":"2022-07-21T14:01:59.465454-04:00"},"22":{"Id":"22","Root":{"X":0.239851,"Y":0.0150856972,"Z":0.7883773},"Timestamp":"2022-07-21T14:02:00.102226-04:00"}},"Decisions":{},"Interactions":{"22":{"Id":"22","Timestamp":"2022-07-21T13:58:04.734162-04:00","WasPickedUp":true,"Name":"Tool Table Calipers"},"24":{"Id":"24","Timestamp":"2022-07-21T13:58:14.006526-04:00","WasPickedUp":true,"Name":"Tool Table Calipers"},"26":{"Id":"26","Timestamp":"2022-07-21T14:01:56.275718-04:00","WasPickedUp":true,"Name":"Tool Table Calipers"},"28":{"Id":"28","Timestamp":"2022-07-21T14:01:59.30867-04:00","WasPickedUp":true,"Name":"Tool Table Calipers"},"30":{"Id":"30","Timestamp":"2022-07-21T14:01:59.921225-04:00","WasPickedUp":true,"Name":"Tool Table Calipers"},"32":{"Id":"32","Timestamp":"2022-07-21T14:03:09.270407-04:00","WasPickedUp":true,"Name":"Tool Table Calipers"},"34":{"Id":"34","Timestamp":"2022-07-21T14:03:14.951185-04:00","WasPickedUp":true,"Name":"Tool Table Calipers"},"36":{"Id":"36","Timestamp":"2022-07-21T14:04:03.914894-04:00","WasPickedUp":true,"Name":"Tool Table Calipers"}},"Activities":{"4":{"Id":"4","Timestamp":"2022-07-21T14:01:56.274517-04:00","ActivityDetail":"First Caliper Pick-Up"},"5":{"Id":"5","Timestamp":"2022-07-21T14:02:03.429583-04:00","ActivityDetail":"Completed caliper testing"}}}